gguf_backend/__init__.py
gguf_backend/__main__.py
gguf_backend-0.0.2.dist-info/LICENSE
gguf_backend-0.0.2.dist-info/WHEEL
gguf_backend-0.0.2.dist-info/METADATA
gguf_backend-0.0.2.dist-info/RECORD
