Metadata-Version: 2.1
Name: gguf-backend
Version: 0.0.2
Summary: backend api
Author-email: calcuis <info@calcu.io>
Classifier: License :: OSI Approved :: MIT License
Project-URL: Repository, https://github.com/calcuis/simple-image-generator-frontend
